At1set_library/__init__.py
At1set_library/main.py
At1set_library-0.0.4.dist-info/LICENSE
At1set_library-0.0.4.dist-info/METADATA
At1set_library-0.0.4.dist-info/WHEEL
At1set_library-0.0.4.dist-info/top_level.txt
At1set_library-0.0.4.dist-info/RECORD
