Metadata-Version: 2.1
Name: At1set-library
Version: 0.0.4
Summary: This is my first test library
Home-page: 
Author: At1set
Author-email: iliya9874329@gmail.com
Project-URL: GitHub, https://github.com/At1set
Classifier: Programming Language :: Python :: 3.11
Classifier: License :: OSI Approved :: MIT License
Classifier: Operating System :: OS Independent
Requires-Python: >=3.6
License-File: LICENSE
Requires-Dist: PyAutoGUI
